taskcraft/__init__.py
taskcraft/agent_tools.py
taskcraft/data_processor.py
taskcraft/gen_atomic_task.py
taskcraft/gen_depth_based_task.py
taskcraft/gen_width_based_task.py
taskcraft/utils.py
taskcraft/oagents/__init__.py
taskcraft/oagents/agent_types.py
taskcraft/oagents/agents.py
taskcraft/oagents/cli.py
taskcraft/oagents/e2b_executor.py
taskcraft/oagents/gradio_ui.py
taskcraft/oagents/knowledge_retrieval.py
taskcraft/oagents/local_python_executor.py
taskcraft/oagents/mdconvert.py
taskcraft/oagents/memory.py
taskcraft/oagents/models.py
taskcraft/oagents/monitoring.py
taskcraft/oagents/similarity.py
taskcraft/oagents/simple_vector_retriever.py
taskcraft/oagents/utils.py
taskcraft/oagents/verify_function.py
taskcraft/oagents/vision_web_browser.py
taskcraft/oagents/workflow.py
taskcraft/oagents/knowledge_base/__init__.py
taskcraft/oagents/knowledge_base/jsonl_to_json.py
taskcraft/oagents/prompts/__init__.py
taskcraft/oagents/prompts/default/ORM.yaml
taskcraft/oagents/prompts/default/ORM_bak.yaml
taskcraft/oagents/prompts/default/PRM.yaml
taskcraft/oagents/prompts/default/PRM_bak.yaml
taskcraft/oagents/prompts/default/__init__.py
taskcraft/oagents/prompts/default/code_agent.yaml
taskcraft/oagents/prompts/default/code_agent_bak.yaml
taskcraft/oagents/prompts/default/list-wise.yaml
taskcraft/oagents/prompts/default/toolcalling_agent.yaml
taskcraft/oagents/prompts/w_think_reflect/__init__.py
taskcraft/oagents/prompts/w_think_reflect/toolcalling_agent.yaml
taskcraft/oagents/prompts/w_think_reflect_and_answer/__init__.py
taskcraft/oagents/prompts/w_think_reflect_and_answer/toolcalling_agent.yaml
taskcraft/oagents/reflectors/__init__.py
taskcraft/oagents/reflectors/search_reflector.py
taskcraft/oagents/reflectors/prompts/search_prompts.yaml
taskcraft/oagents/tools/__init__.py
taskcraft/oagents/tools/_function_type_hints_utils.py
taskcraft/oagents/tools/async_web_crawler_tool.py
taskcraft/oagents/tools/default_tools.py
taskcraft/oagents/tools/text_inspector_tool.py
taskcraft-0.3.0.dist-info/licenses/LICENSE
taskcraft-0.3.0.dist-info/licenses/NOTICE
taskcraft-0.3.0.dist-info/METADATA
taskcraft-0.3.0.dist-info/WHEEL
taskcraft-0.3.0.dist-info/top_level.txt
taskcraft-0.3.0.dist-info/RECORD
