Metadata-Version: 2.4
Name: taskcraft
Version: 0.3.0
Summary: TaskCraft: an automated workflow for generating difficulty-scalable, multi-tool, and verifiable agentic tasks with execution trajectories. It also expands atomic tasks using depth-based and width-based extensions to create structurally and hierarchically complex challenges.
Author-email: Dingfeng Shi <shidingfeng@oppo.com>, Jingyi Cao <caojingyi@oppo.com>, Qianben Chen <chenqianben@oppo.com>
License: MIT License
Classifier: Programming Language :: Python :: 3
Classifier: Operating System :: OS Independent
License-File: LICENSE
License-File: NOTICE
Requires-Dist: accelerate
Requires-Dist: agentops
Requires-Dist: anthropic
Requires-Dist: apify_client
Requires-Dist: beautifulsoup4
Requires-Dist: Bio
Requires-Dist: biopython
Requires-Dist: botocore
Requires-Dist: camel-ai==0.2.66
Requires-Dist: cohere
Requires-Dist: crawl4ai
Requires-Dist: docx2txt
Requires-Dist: duckduckgo_search==8.0.2
Requires-Dist: e2b_code_interpreter==1.5.1
Requires-Dist: firecrawl==2.7.1
Requires-Dist: google_search_results
Requires-Dist: gradio
Requires-Dist: gradio_client
Requires-Dist: helium==5.1.1
Requires-Dist: huggingface_hub>=0.31.2
Requires-Dist: imageio
Requires-Dist: ipython
Requires-Dist: Jinja2==3.1.6
Requires-Dist: langchain==0.3.25
Requires-Dist: langchain_text_splitters==0.3.8
Requires-Dist: langid==1.1.6
Requires-Dist: litellm==1.72.2
Requires-Dist: mammoth
Requires-Dist: markdownify
Requires-Dist: mmh3
Requires-Dist: neo4j
Requires-Dist: numpy
Requires-Dist: openpyxl==3.1.5
Requires-Dist: pandas>=2.3.0
Requires-Dist: pdfminer
Requires-Dist: pdfminer_six
Requires-Dist: pdfplumber
Requires-Dist: protobuf==5.29.4
Requires-Dist: puremagic
Requires-Dist: pydub
Requires-Dist: PyMuPDF
Requires-Dist: pymilvus
Requires-Dist: python-dotenv
Requires-Dist: python_pptx
Requires-Dist: PyYAML
Requires-Dist: qdrant_client
Requires-Dist: rank_bm25
Requires-Dist: Requests
Requires-Dist: rich
Requires-Dist: scikit_learn
Requires-Dist: selenium
Requires-Dist: sentence_transformers
Requires-Dist: serpapi==0.1.5
Requires-Dist: soundfile
Requires-Dist: speechrecognition
Requires-Dist: tqdm
Requires-Dist: transformers
Requires-Dist: unstructured
Requires-Dist: youtube_transcript_api
Requires-Dist: newspaper3k
Provides-Extra: dev
Requires-Dist: pytest>=7.0; extra == "dev"
Requires-Dist: black>=23.0; extra == "dev"
Requires-Dist: isort>=5.0; extra == "dev"
Dynamic: license-file
